Metadata-Version: 2.1
Name: odoo14-addon-l10n_br_base
Version: 14.0.3.16.3
Summary: Customization of base module for implementations in Brazil.
Home-page: https://github.com/OCA/l10n-brazil
Author: Akretion,Odoo Community Association (OCA)
Author-email: support@odoo-community.org
License: AGPL-3
Classifier: Programming Language :: Python
Classifier: Framework :: Odoo
Classifier: Framework :: Odoo :: 14.0
Classifier: License :: OSI Approved :: GNU Affero General Public License v3
Classifier: Development Status :: 6 - Mature
Requires-Python: >=3.6
Requires-Dist: email-validator
Requires-Dist: erpbrasil.base
Requires-Dist: num2words
Requires-Dist: odoo<14.1dev,>=14.0a
Requires-Dist: phonenumbers
